{
    "chapter": 6,
    "id": 25,
    "key": 2,
    "experiences": [
        125,
        125,
        125
    ],
    "objectiveType": [
        2,
        2,
        2
    ],
    "objective": [
        14,
        15,
        16
    ],
    "limitType": [
        1,
        1,
        1
    ],
    "limit": [
        65,
        65,
        65
    ],
    "conditionType": [
        1,
        1,
        1
    ],
    "waves": [
        "23_144_33_124_14_13_34_2_14_2_333_22_133_33_114",
        "23_13_12_44_333_112_34_33_124_23_14_4_123_24_133",
        "24_133_23_44_23_414_4_112_43_32_113_22_111_13_333_13",
		"23_144_33_124_14_13_34_2_14_2_333_22_133_33_114",
        "23_13_12_44_333_112_34_33_124_23_14_4_123_24_133",
        "24_133_23_44_23_414_4_112_43_32_113_22_111_13_333_13"
    ],
    "foodSpawnPercents": [
        "",
        "",
        ""
    ],
    "customerSpeed": [
        4,
        4,
        4
    ],
    "customerIntervals": [
        3,
        3,
        3	
    ],
    "customerWaitTime": [
        24,
        22,
        20
    ]
}